streamsnatcher/__init__.py
streamsnatcher/cli.py
streamsnatcher/core.py
streamsnatcher/FreeResources/FreeResources/__init__.py
streamsnatcher/FreeResources/tests/test_basic.py
streamsnatcher/streamsnatcher/streamsnatcher/__init__.py
streamsnatcher/streamsnatcher/tests/test_basic.py
streamsnatcher-0.1.2.dist-info/licenses/LICENSE.md
streamsnatcher-0.1.2.dist-info/METADATA
streamsnatcher-0.1.2.dist-info/WHEEL
streamsnatcher-0.1.2.dist-info/entry_points.txt
streamsnatcher-0.1.2.dist-info/top_level.txt
streamsnatcher-0.1.2.dist-info/RECORD
