Metadata-Version: 2.4
Name: streamsnatcher
Version: 0.1.2
Summary: StreamSnatcher — rip encode and capture streams with style
Author-email: "C. Hirschauer" <c.hirschauer@gmail.com>
License-Expression: MIT
Project-URL: Homepage, https://github.com/74Thirsty/streamsnatcher
Requires-Python: >=3.9
License-File: LICENSE.md
Dynamic: license-file
